fair_perf_ml-0.1.0.dist-info/METADATA
fair_perf_ml-0.1.0.dist-info/WHEEL
fair_perf_ml-0.1.0.dist-info/licenses/LICENSE
fair_perf_ml/data_bias.py
fair_perf_ml/models.py
fair_perf_ml/__init__.py
fair_perf_ml/.github/workflows/CI.yml
fair_perf_ml/.gitignore
fair_perf_ml/model_perf.py
fair_perf_ml/_internal.py
fair_perf_ml/model_bias.py
fair_perf_ml/_fair_perf_ml.cpython-312-x86_64-linux-gnu.so
fair_perf_ml-0.1.0.dist-info/RECORD
