Metadata-Version: 2.4
Name: fair_perf_ml
Version: 0.1.0
Classifier: Programming Language :: Rust
Classifier: Programming Language :: Python :: Implementation :: CPython
Classifier: Programming Language :: Python :: Implementation :: PyPy
Requires-Dist: pydantic>=2.9.2
Requires-Dist: numpy>=2.0.0
Requires-Dist: orjson>=3.9.0
License-File: LICENSE
Summary: A package for evalutating machine learning models for pre training and post training biasin addition to evaluting the model for performance at training time and runtime.
Keywords: machine learning,bias,py03,rust
Author-email: Kilian Hammersmith <kilianhammersmith@gmail.com>
Maintainer-email: Kilian Hammersmith <kilianhammersmith@gmail.com>
Requires-Python: >=3.8
